clops
